LICENSE.md
MANIFEST.in
README.rst
setup.py
django_appregistration/__init__.py
django_appregistration.egg-info/PKG-INFO
django_appregistration.egg-info/SOURCES.txt
django_appregistration.egg-info/dependency_links.txt
django_appregistration.egg-info/requires.txt
django_appregistration.egg-info/top_level.txt